playgwtc/__init__.py
playgwtc/fetch_data.py
playgwtc/main.py
playgwtc/plotter.py
playgwtc-0.2.0.dist-info/licenses/LICENSE
playgwtc-0.2.0.dist-info/METADATA
playgwtc-0.2.0.dist-info/WHEEL
playgwtc-0.2.0.dist-info/entry_points.txt
playgwtc-0.2.0.dist-info/top_level.txt
playgwtc-0.2.0.dist-info/RECORD
