Metadata-Version: 2.4
Name: playgwtc
Version: 0.2.0
Summary: A tool to fetch, process, and visualize data for Gravitational Wave events.
Author-email: Devesh Giri <deveshgiri.edu@gmail.com>, Danielle N Smart <danielle.naomi.smart@gmail.com>, Adiba Amira <asiddiqa@brynmawr.edu>
License: MIT License
Classifier: Programming Language :: Python :: 3
Classifier: Operating System :: OS Independent
Classifier: Topic :: Scientific/Engineering :: Astronomy
Requires-Python: >=3.9
License-File: LICENSE
Requires-Dist: pandas
Requires-Dist: matplotlib
Requires-Dist: numpy
Requires-Dist: gwpy
Requires-Dist: pycbc
Requires-Dist: requests
Dynamic: license-file
